dd2482_course_automation/__init__.py
dd2482_course_automation/__main__.py
dd2482_course_automation/exceptions.py
dd2482_course_automation/main.py
dd2482_course_automation-0.1.6.dist-info/entry_points.txt
dd2482_course_automation-0.1.6.dist-info/WHEEL
dd2482_course_automation-0.1.6.dist-info/METADATA
dd2482_course_automation-0.1.6.dist-info/RECORD
