Metadata-Version: 2.1
Name: dd2482-course-automation
Version: 0.1.6
Summary: 
Author: landeholt
Author-email: johnlan@kth.se
Requires-Python: >=3.9,<4.0
Classifier: Programming Language :: Python :: 3
Classifier: Programming Language :: Python :: 3.10
Classifier: Programming Language :: Python :: 3.9
Requires-Dist: pytz (>=2022.1,<2023.0)
Requires-Dist: requests (>=2.27.1,<3.0.0)
